Workbook
Name anos_investimento: ' F.I'!$K$16
Name aporte: ' F.I'!$K$14
Name dividendo_mensal: ' F.I'!$K$22
Name patrimonio_acumulado: ' F.I'!$K$20
Name rendimento_carteira: ' F.I'!$O$16
Name salario: ' F.I'!$N$15
Name sugestao_invest: ' F.I'!$N$17
Name taxa_mensal: ' F.I'!$K$18
Name taxa_mensal_rendimento: ' F.I'!$K$18

Sheet  F.I
I14: Quanto investir por mês ? | K14: 500 | N14: Configurações
N15: Salário | O15: 5000
I16: Por quantos anos ? | K16: 5 | N16: Rendimento Carteira | O16: 0.006
N17: Rendimento Investimento | O17: 1500
I18: Taxa de rendimento mensal ? | K18: 0.01079
N19: Perfil | O19: Valor investido mensalmente
I20: Patrimonio acumulado ? | K20: =FV(K18,K16*12,K14*-1) -> 41888.457 | N20: Agressivo | O20: 500
I22: Dividendo mensal | K22: =K20*$O$16 -> 251.33074
N23: Tipo de FI | O23: % Sugerido | P23: Valores
N24: Papel | O24: =_xlfn.XLOOKUP($N$20&"-"&N24,Planilha1!A:A,Planilha1!D:D,"-") -> 0.5 | P24: =O24*$O$20 -> 250
I25: Cenários | K25: Dividendo | N25: Tijolo | O25: 0.3 | P25: =O25*$O$20 -> 150
I26: Quanto em 2 Anos ? | J26: =FV($K$18,T26*12,$K$14*-1) -> 13613.814 | K26: =J26*rendimento_carteira -> 81.682882 | N26: Hibridos | O26: =_xlfn.XLOOKUP($N$20&"-"&N26,Planilha1!A:A,Planilha1!D:D,"-") -> 0.05 | P26: =O26*$O$20 -> 25 | T26: 2
I27: Quanto em 5 Anos ? | J27: =FV($K$18,T27*12,$K$14*-1) -> 41888.457 | K27: =J27*rendimento_carteira -> 251.33074 | N27: Fofs | O27: =_xlfn.XLOOKUP($N$20&"-"&N27,Planilha1!A:A,Planilha1!D:D,"-") -> 0.05 | P27: =O27*$O$20 -> 25 | T27: 5
I28: Quanto em 10 Anos ? | J28: =FV($K$18,T28*12,$K$14*-1) -> 121642.11 | K28: =J28*rendimento_carteira -> 729.85264 | N28: Desenvolvimento | O28: =_xlfn.XLOOKUP($N$20&"-"&N28,Planilha1!A:A,Planilha1!D:D,"-") -> 0.2 | P28: =O28*$O$20 -> 100 | T28: 10
I29: Quanto em 20 Anos ? | J29: =FV($K$18,T29*12,$K$14*-1) -> 562599.2 | K29: =J29*rendimento_carteira -> 3375.5952 | N29: Hotelarias | O29: =_xlfn.XLOOKUP($N$20&"-"&N29,Planilha1!A:A,Planilha1!D:D,"-") -> 0.1 | P29: =O29*$O$20 -> 50 | T29: 20
I30: Quanto em 30 Anos ? | J30: =FV($K$18,T30*12,$K$14*-1) -> 2161084.8 | K30: =J30*rendimento_carteira -> 12966.509 | P30: =SUM(P24:P29) -> 600 | T30: 30

Sheet Planilha1
A1: Chave composta | B1: Perfil | C1: Tipo de FI | D1: %
A2: =B2&"-"&C2 -> Conservador-Papel | B2: Conservador | C2: Papel | D2: 0.3
A3: =B3&"-"&C3 -> Conservador-Tijolo | B3: Conservador | C3: Tijolo | D3: 0.5
A4: =B4&"-"&C4 -> Conservador-Hibridos | B4: Conservador | C4: Hibridos | D4: 0.1
A5: =B5&"-"&C5 -> Conservador-Fofs | B5: Conservador | C5: Fofs | D5: 0.1
A6: =B6&"-"&C6 -> Conservador-Desenvolvimento | B6: Conservador | C6: Desenvolvimento | D6: 0
A7: =B7&"-"&C7 -> Conservador-Hotelarias | B7: Conservador | C7: Hotelarias | D7: 0
A8: =B8&"-"&C8 -> Moderado-Papel | B8: Moderado | C8: Papel | D8: 0.32
A9: =B9&"-"&C9 -> Moderado-Tijolo | B9: Moderado | C9: Tijolo | D9: 0.4
A10: =B10&"-"&C10 -> Moderado-Hibridos | B10: Moderado | C10: Hibridos | D10: 0.08
A11: =B11&"-"&C11 -> Moderado-Fofs | B11: Moderado | C11: Fofs | D11: 0.1
A12: =B12&"-"&C12 -> Moderado-Desenvolvimento | B12: Moderado | C12: Desenvolvimento | D12: 0.1
A13: =B13&"-"&C13 -> Moderado-Hotelarias | B13: Moderado | C13: Hotelarias | D13: 0.1
... A19: =B19&"-"&C19 -> Agressivo-Hotelarias | B19: Agressivo | C19: Hotelarias | D19: 0.1
